aesara/__init__.py
aesara/_version.py
aesara/assert_op.py
aesara/breakpoint.py
aesara/configdefaults.py
aesara/configparser.py
aesara/gradient.py
aesara/ifelse.py
aesara/printing.py
aesara/py.typed
aesara/raise_op.py
aesara/updates.py
aesara/utils.py
aesara/version.py
aesara/bin/__init__.py
aesara/bin/aesara_cache.py
aesara/compile/__init__.py
aesara/compile/builders.py
aesara/compile/compiledir.py
aesara/compile/compilelock.py
aesara/compile/debugmode.py
aesara/compile/io.py
aesara/compile/mode.py
aesara/compile/monitormode.py
aesara/compile/nanguardmode.py
aesara/compile/ops.py
aesara/compile/profiling.py
aesara/compile/sharedvalue.py
aesara/compile/function/__init__.py
aesara/compile/function/pfunc.py
aesara/compile/function/types.py
aesara/d3viz/__init__.py
aesara/d3viz/d3viz.py
aesara/d3viz/formatting.py
aesara/d3viz/css/d3-context-menu.css
aesara/d3viz/css/d3viz.css
aesara/d3viz/html/template.html
aesara/d3viz/js/d3-context-menu.js
aesara/d3viz/js/d3.v3.min.js
aesara/d3viz/js/d3viz.js
aesara/d3viz/js/dagre-d3.min.js
aesara/d3viz/js/graphlib-dot.min.js
aesara/graph/__init__.py
aesara/graph/basic.py
aesara/graph/destroyhandler.py
aesara/graph/features.py
aesara/graph/fg.py
aesara/graph/kanren.py
aesara/graph/null_type.py
aesara/graph/op.py
aesara/graph/opt.py
aesara/graph/opt_utils.py
aesara/graph/optdb.py
aesara/graph/sched.py
aesara/graph/toolbox.py
aesara/graph/type.py
aesara/graph/unify.py
aesara/graph/utils.py
aesara/graph/rewriting/__init__.py
aesara/graph/rewriting/basic.py
aesara/graph/rewriting/db.py
aesara/graph/rewriting/kanren.py
aesara/graph/rewriting/unify.py
aesara/graph/rewriting/utils.py
aesara/link/__init__.py
aesara/link/basic.py
aesara/link/utils.py
aesara/link/vm.py
aesara/link/c/__init__.py
aesara/link/c/basic.py
aesara/link/c/cmodule.py
aesara/link/c/cutils.py
aesara/link/c/cvm.py
aesara/link/c/exceptions.py
aesara/link/c/interface.py
aesara/link/c/lazylinker_c.py
aesara/link/c/op.py
aesara/link/c/params_type.py
aesara/link/c/type.py
aesara-2.9.2.dist-info/METADATA
aesara-2.9.2.dist-info/WHEEL
aesara-2.9.2.dist-info/entry_points.txt
aesara-2.9.2.dist-info/licenses/LICENSE.txt
aesara-2.9.2.dist-info/RECORD
